poisson/__init__.py
poisson/api.py
poisson/core.py
poisson/examples/__init__.py
poisson/examples/horse_with_normals.xyz
poisson/examples/ply_from_array.py
poisson/lib/libpypoisson_big.so
poisson/lib/libpypoisson_std.so
poisson/src/Wrapper.cpp
poisson/src/WrapperApi.h
poisson/tools/PoissonReconDump.cpp
pypoisson2.libs/libgomp-16c68465.so.1.0.0
pypoisson2-1.0.0.dist-info/METADATA
pypoisson2-1.0.0.dist-info/WHEEL
pypoisson2-1.0.0.dist-info/top_level.txt
pypoisson2-1.0.0.dist-info/RECORD
pypoisson2-1.0.0.dist-info/licenses/LICENSE
pypoisson2-1.0.0.dist-info/sboms/auditwheel.cdx.json
