Metadata-Version: 2.4
Name: pypoisson2
Version: 1.0.0
Summary: Modern Python bindings for Poisson Surface Reconstruction (v18.74)
Home-page: https://github.com/mkazhdan/PoissonRecon
Author: Michael Kazhdan (Library), Adaptive Solvers (Bindings)
License: BSD-3-Clause
Classifier: Programming Language :: Python :: 3
Classifier: Programming Language :: C++
Classifier: License :: OSI Approved :: BSD License
Classifier: Operating System :: POSIX :: Linux
Requires-Python: >=3.9
License-File: LICENSE
Requires-Dist: numpy
Dynamic: author
Dynamic: classifier
Dynamic: description
Dynamic: description-content-type
Dynamic: home-page
Dynamic: license
Dynamic: license-file
Dynamic: requires-dist
Dynamic: requires-python
Dynamic: summary
